setup.py
mmiexample/__init__.py
mmiexample/main.py
mothermayi_example.egg-info/PKG-INFO
mothermayi_example.egg-info/SOURCES.txt
mothermayi_example.egg-info/dependency_links.txt
mothermayi_example.egg-info/entry_points.txt
mothermayi_example.egg-info/requires.txt
mothermayi_example.egg-info/top_level.txt