Metadata-Version: 1.0
Name: mothermayi-example
Version: 0.1
Summary: An example plugin for mothermayi
Home-page: https://github.com/EliRibble/mothermayi-example
Author: Eli Ribble
Author-email: junk@theribbles.org
License: UNKNOWN
Platform: UNKNOWN
